MICTI/GM.py
MICTI/GeoMinner.py
MICTI/HdpModel.py
MICTI/Kmeans.py
MICTI/MARKER.py
MICTI/MARKERS.py
MICTI/__init__.py
MICTI/heatmap.py
MICTI/normalize.py
MICTI/radarPlot.py
MICTI-0.2.0.dist-info/LICENSE
MICTI-0.2.0.dist-info/METADATA
MICTI-0.2.0.dist-info/WHEEL
MICTI-0.2.0.dist-info/top_level.txt
MICTI-0.2.0.dist-info/RECORD
