Metadata-Version: 2.1
Name: MICTI
Version: 0.2.0
Summary: Feature extraction approach in single-cell gene expression profiling for cell-type marker identification.
Home-page: https://github.com/insilicolife/micti
Author: Nigatu Ayele
Author-email: naodm2006awet4@gmail.com
License: UNKNOWN
Platform: UNKNOWN
Classifier: Programming Language :: Python :: 3.6
Classifier: License :: OSI Approved :: MIT License
Classifier: Operating System :: OS Independent
Requires-Dist: numpy
Requires-Dist: pandas
Requires-Dist: scipy
Requires-Dist: scikit-learn
Requires-Dist: matplotlib
Requires-Dist: gensim
Requires-Dist: gprofiler
Requires-Dist: seaborn
Requires-Dist: pyensembl
Requires-Dist: bs4
Requires-Dist: requests
Requires-Dist: html5lib
Requires-Dist: umap-learn
